color_crafter_py/__init__.py
color_crafter_py/__main__.py
color_crafter_py/base.py
color_crafter_py/cli.py
color_crafter_py-0.1.1.dist-info/LICENSE
color_crafter_py-0.1.1.dist-info/METADATA
color_crafter_py-0.1.1.dist-info/WHEEL
color_crafter_py-0.1.1.dist-info/entry_points.txt
color_crafter_py-0.1.1.dist-info/top_level.txt
color_crafter_py-0.1.1.dist-info/RECORD
