Metadata-Version: 2.1
Name: color-crafter-py
Version: 0.1.1
Summary: A powerful and easy-to-use Python library for adding colors and styles to text printed on your terminal. Can be used with custom RGB colors. Created by WernerLuiz92
Home-page: https://github.com/WernerLuiz92/color_crafter_py/
Author: WernerLuiz92
License-File: LICENSE
Provides-Extra: test
Requires-Dist: pytest ; extra == 'test'
Requires-Dist: coverage ; extra == 'test'
Requires-Dist: flake8 ; extra == 'test'
Requires-Dist: black ; extra == 'test'
Requires-Dist: isort ; extra == 'test'
Requires-Dist: pytest-cov ; extra == 'test'
Requires-Dist: mypy ; extra == 'test'
Requires-Dist: gitchangelog ; extra == 'test'
Requires-Dist: mkdocs ; extra == 'test'
